{
  "gizmos-infos": {
    "is2D": true,
    "is3DIcon": false,
    "iconSize": 2,
    "gridVisible": true,
    "originAxis2D": {
      "x_visible": true,
      "y_visible": true,
      "z_visible": false
    },
    "originAxis3D": {
      "x_visible": true,
      "y_visible": false,
      "z_visible": true
    },
    "gridColor": [
      85,
      85,
      85,
      255
    ],
    "transformToolName": "position",
    "pivot": "pivot",
    "coordinate": "local",
    "toolsVisibility3d": true
  },
  "__version__": "1.0.3",
  "builder": {
    "taskOptionsMap": {},
    "__version__": "1.3.9"
  },
  "snap-configs": {
    "position": {
      "x": 1,
      "y": 1,
      "z": 1
    },
    "rotation": 1,
    "scale": 1,
    "isPositionSnapEnabled": false,
    "isRotationSnapEnabled": false,
    "isScaleSnapEnabled": false
  },
  "rect-snap-configs": {
    "enableSnapping": true,
    "snapThreshold": 4
  },
  "float-window": {
    "position": {
      "cc": {
        "Camera": {
          "dock": false,
          "top": null,
          "bottom": 10,
          "left": null,
          "right": 10
        }
      }
    }
  },
  "camera-infos": {
    "f63c30f5-9b00-4554-bf40-5b498d0c477c": {
      "position": {
        "x": 540,
        "y": 960.1685393258429,
        "z": 5000
      },
      "rotation": {
        "x": 0,
        "y": 0,
        "z": 0,
        "w": 1
      },
      "viewCenter": {
        "x": 0,
        "y": 0,
        "z": 0
      },
      "contentRect": {
        "x": 0,
        "y": 1.1368683772161603e-13,
        "width": 249.19999999999996,
        "height": 443.1
      },
      "scale": 0.23074074074074072
    },
    "c1bc1498-015a-4dd1-97b8-127884b52f31": {
      "position": {
        "x": 540,
        "y": 960.1685393258429,
        "z": 5000
      },
      "rotation": {
        "x": 0,
        "y": 0,
        "z": 0,
        "w": 1
      },
      "viewCenter": {
        "x": 0,
        "y": 0,
        "z": 0
      },
      "contentRect": {
        "x": 0,
        "y": 1.1368683772161603e-13,
        "width": 249.19999999999996,
        "height": 443.1
      },
      "scale": 0.23074074074074072
    },
    "23f4bc2f-cb61-4569-8d05-89e8797959a9": {
      "position": {
        "x": 540,
        "y": 960.1685393258429,
        "z": 5000
      },
      "rotation": {
        "x": 0,
        "y": 0,
        "z": 0,
        "w": 1
      },
      "viewCenter": {
        "x": 0,
        "y": 0,
        "z": 0
      },
      "contentRect": {
        "x": 0,
        "y": 1.1368683772161603e-13,
        "width": 249.19999999999996,
        "height": 443.1
      },
      "scale": 0.23074074074074072
    },
    "190151c2-7a08-4fb7-a224-af24a79e9fd2": {
      "position": {
        "x": 540,
        "y": 960.1685393258429,
        "z": 5000
      },
      "rotation": {
        "x": 0,
        "y": 0,
        "z": 0,
        "w": 1
      },
      "viewCenter": {
        "x": 0,
        "y": 0,
        "z": 0
      },
      "contentRect": {
        "x": 0,
        "y": 1.1368683772161603e-13,
        "width": 249.19999999999996,
        "height": 443.1
      },
      "scale": 0.23074074074074072
    },
    "28c2dff9-1824-46ee-98ec-21aafdba0d73": {
      "position": {
        "x": 540,
        "y": 960.1685393258429,
        "z": 5000
      },
      "rotation": {
        "x": 0,
        "y": 0,
        "z": 0,
        "w": 1
      },
      "viewCenter": {
        "x": 0,
        "y": 0,
        "z": 0
      },
      "contentRect": {
        "x": 0,
        "y": 1.1368683772161603e-13,
        "width": 249.19999999999996,
        "height": 443.1
      },
      "scale": 0.23074074074074072
    },
    "ea9c3c8c-ad25-4be1-b0fb-48652a4289c3": {
      "position": {
        "x": 540,
        "y": 960.1685393258429,
        "z": 5000
      },
      "rotation": {
        "x": 0,
        "y": 0,
        "z": 0,
        "w": 1
      },
      "viewCenter": {
        "x": 0,
        "y": 0,
        "z": 0
      },
      "contentRect": {
        "x": 0,
        "y": 1.1368683772161603e-13,
        "width": 249.19999999999996,
        "height": 443.1
      },
      "scale": 0.23074074074074072
    },
    "8f4b7722-bdd9-4f92-9b39-7b944a1bb4b0": {
      "position": {
        "x": 540,
        "y": 960.1685393258429,
        "z": 5000
      },
      "rotation": {
        "x": 0,
        "y": 0,
        "z": 0,
        "w": 1
      },
      "viewCenter": {
        "x": 0,
        "y": 0,
        "z": 0
      },
      "contentRect": {
        "x": 0,
        "y": 1.1368683772161603e-13,
        "width": 249.19999999999996,
        "height": 443.1
      },
      "scale": 0.23074074074074072
    },
    "98ff4829-3c5a-43bc-a42a-4697202840ec": {
      "position": {
        "x": 540,
        "y": 960,
        "z": 5000
      },
      "rotation": {
        "x": 0,
        "y": 0,
        "z": 0,
        "w": 1
      },
      "viewCenter": {
        "x": 0,
        "y": 0,
        "z": 0
      },
      "contentRect": {
        "x": -471.6855307433466,
        "y": -411.4285714285715,
        "width": 689,
        "height": 934
      },
      "scale": 0.34052083333333333
    },
    "3b12c6fb-93c6-4f2d-9733-fd072f55d35d": {
      "position": {
        "x": 540,
        "y": 960.1685393258429,
        "z": 5000
      },
      "rotation": {
        "x": 0,
        "y": 0,
        "z": 0,
        "w": 1
      },
      "viewCenter": {
        "x": 0,
        "y": 0,
        "z": 0
      },
      "contentRect": {
        "x": 0,
        "y": 1.1368683772161603e-13,
        "width": 249.19999999999996,
        "height": 443.1
      },
      "scale": 0.23074074074074072
    },
    "7b1ff178-765d-49e6-a1d3-0897373e0532": {
      "position": {
        "x": 539.9999999999999,
        "y": 960,
        "z": 5000
      },
      "rotation": {
        "x": 0,
        "y": 0,
        "z": 0,
        "w": 1
      },
      "viewCenter": {
        "x": 0,
        "y": 0,
        "z": 0
      },
      "contentRect": {
        "x": 0,
        "y": 0,
        "width": 367.7625,
        "height": 653.8
      },
      "scale": 0.34052083333333333
    },
    "c2ba1d29-5ca3-4e9d-8d11-0166ffc5b0c0": {
      "position": {
        "x": 540.0000000000002,
        "y": 960.0000000000002,
        "z": 5000
      },
      "rotation": {
        "x": 0,
        "y": 0,
        "z": 0,
        "w": 1
      },
      "viewCenter": {
        "x": 0,
        "y": 0,
        "z": 0
      },
      "contentRect": {
        "x": 0,
        "y": 1.1368683772161603e-13,
        "width": 393.75,
        "height": 700
      },
      "scale": 0.3645833333333333
    },
    "e46b84c0-c2f0-42d6-b3cb-c5496df79b7a": {
      "position": {
        "x": 540,
        "y": 960,
        "z": 5000
      },
      "rotation": {
        "x": 0,
        "y": 0,
        "z": 0,
        "w": 1
      },
      "viewCenter": {
        "x": 0,
        "y": 0,
        "z": 0
      },
      "contentRect": {
        "x": 0,
        "y": 0,
        "width": 367.7625,
        "height": 653.8
      },
      "scale": 0.34052083333333333
    },
    "af08d2ac-23c4-4651-9230-aea1a154fd26": {
      "position": {
        "x": 540.0000000000002,
        "y": 960.0000000000002,
        "z": 5000
      },
      "rotation": {
        "x": 0,
        "y": 0,
        "z": 0,
        "w": 1
      },
      "viewCenter": {
        "x": 0,
        "y": 0,
        "z": 0
      },
      "contentRect": {
        "x": 0,
        "y": 1.1368683772161603e-13,
        "width": 393.75,
        "height": 700
      },
      "scale": 0.3645833333333333
    },
    "677e48b9-ddcb-4482-8537-ed1f4bc7b9d1": {
      "position": {
        "x": 540,
        "y": 960.1685393258429,
        "z": 5000
      },
      "rotation": {
        "x": 0,
        "y": 0,
        "z": 0,
        "w": 1
      },
      "viewCenter": {
        "x": 0,
        "y": 0,
        "z": 0
      },
      "contentRect": {
        "x": 0,
        "y": 1.1368683772161603e-13,
        "width": 249.19999999999996,
        "height": 443.1
      },
      "scale": 0.23074074074074072
    },
    "c9eaa10a-8107-4797-a73c-517650567f3f": {
      "position": {
        "x": 540,
        "y": 960.1685393258429,
        "z": 5000
      },
      "rotation": {
        "x": 0,
        "y": 0,
        "z": 0,
        "w": 1
      },
      "viewCenter": {
        "x": 0,
        "y": 0,
        "z": 0
      },
      "contentRect": {
        "x": 0,
        "y": 1.1368683772161603e-13,
        "width": 249.19999999999996,
        "height": 443.1
      },
      "scale": 0.23074074074074072
    },
    "0124516a-207a-433c-b35b-af55e5f53a2c": {
      "position": {
        "x": 544.76,
        "y": 1288.1749999999997,
        "z": 5000
      },
      "rotation": {
        "x": 0,
        "y": 0,
        "z": 0,
        "w": 1
      },
      "viewCenter": {
        "x": 0,
        "y": 0,
        "z": 0
      },
      "contentRect": {
        "x": 424.76,
        "y": 1168.175,
        "width": 427.70000000000005,
        "height": 427.70000000000005
      },
      "scale": 1.7820833333333335
    },
    "f402435c-a277-449f-8d0f-2312861d264c": {
      "position": {
        "x": 540,
        "y": 960.1685393258429,
        "z": 5000
      },
      "rotation": {
        "x": 0,
        "y": 0,
        "z": 0,
        "w": 1
      },
      "viewCenter": {
        "x": 0,
        "y": 0,
        "z": 0
      },
      "contentRect": {
        "x": 0,
        "y": 1.1368683772161603e-13,
        "width": 249.19999999999996,
        "height": 443.1
      },
      "scale": 0.23074074074074072
    },
    "1ef0b093-4dbb-4bf2-b507-5d18b22bed20": {
      "position": {
        "x": 540,
        "y": 960.1685393258429,
        "z": 5000
      },
      "rotation": {
        "x": 0,
        "y": 0,
        "z": 0,
        "w": 1
      },
      "viewCenter": {
        "x": 0,
        "y": 0,
        "z": 0
      },
      "contentRect": {
        "x": 0,
        "y": 1.1368683772161603e-13,
        "width": 249.19999999999996,
        "height": 443.1
      },
      "scale": 0.23074074074074072
    },
    "2957e9ed-0bc7-4938-8bab-a8031eb34703": {
      "position": {
        "x": 540,
        "y": 960.1685393258429,
        "z": 5000
      },
      "rotation": {
        "x": 0,
        "y": 0,
        "z": 0,
        "w": 1
      },
      "viewCenter": {
        "x": 0,
        "y": 0,
        "z": 0
      },
      "contentRect": {
        "x": 0,
        "y": 1.1368683772161603e-13,
        "width": 249.19999999999996,
        "height": 443.1
      },
      "scale": 0.23074074074074072
    },
    "c04774ae-a060-4488-89d2-57984e1ae0f9": {
      "position": {
        "x": 540,
        "y": 960.1685393258429,
        "z": 5000
      },
      "rotation": {
        "x": 0,
        "y": 0,
        "z": 0,
        "w": 1
      },
      "viewCenter": {
        "x": 0,
        "y": 0,
        "z": 0
      },
      "contentRect": {
        "x": 0,
        "y": 1.1368683772161603e-13,
        "width": 249.19999999999996,
        "height": 443.1
      },
      "scale": 0.23074074074074072
    },
    "e8e20e01-280d-41a6-977e-cd0a913a9cd5": {
      "position": {
        "x": 540,
        "y": 960.1685393258429,
        "z": 5000
      },
      "rotation": {
        "x": 0,
        "y": 0,
        "z": 0,
        "w": 1
      },
      "viewCenter": {
        "x": 0,
        "y": 0,
        "z": 0
      },
      "contentRect": {
        "x": 0,
        "y": 1.1368683772161603e-13,
        "width": 249.19999999999996,
        "height": 443.1
      },
      "scale": 0.23074074074074072
    },
    "b36a2af2-cc8f-44d0-bb38-0dc6748c8223": {
      "position": {
        "x": 540,
        "y": 960.1685393258429,
        "z": 5000
      },
      "rotation": {
        "x": 0,
        "y": 0,
        "z": 0,
        "w": 1
      },
      "viewCenter": {
        "x": 0,
        "y": 0,
        "z": 0
      },
      "contentRect": {
        "x": 0,
        "y": 1.1368683772161603e-13,
        "width": 249.19999999999996,
        "height": 443.1
      },
      "scale": 0.23074074074074072
    },
    "edfbd224-dffc-4a84-b2e6-2737f2c3d83e": {
      "position": {
        "x": 540,
        "y": 960.1685393258429,
        "z": 5000
      },
      "rotation": {
        "x": 0,
        "y": 0,
        "z": 0,
        "w": 1
      },
      "viewCenter": {
        "x": 0,
        "y": 0,
        "z": 0
      },
      "contentRect": {
        "x": 0,
        "y": 1.1368683772161603e-13,
        "width": 249.19999999999996,
        "height": 443.1
      },
      "scale": 0.23074074074074072
    },
    "0f0183ae-8373-470c-801f-2d9bdd218678": {
      "position": {
        "x": 540,
        "y": 960.1685393258429,
        "z": 5000
      },
      "rotation": {
        "x": 0,
        "y": 0,
        "z": 0,
        "w": 1
      },
      "viewCenter": {
        "x": 0,
        "y": 0,
        "z": 0
      },
      "contentRect": {
        "x": 0,
        "y": 1.1368683772161603e-13,
        "width": 249.19999999999996,
        "height": 443.1
      },
      "scale": 0.23074074074074072
    },
    "19e466cd-7354-4bb0-9458-98a49c902166": {
      "position": {
        "x": 540,
        "y": 960.1685393258429,
        "z": 5000
      },
      "rotation": {
        "x": 0,
        "y": 0,
        "z": 0,
        "w": 1
      },
      "viewCenter": {
        "x": 0,
        "y": 0,
        "z": 0
      },
      "contentRect": {
        "x": 0,
        "y": 1.1368683772161603e-13,
        "width": 249.19999999999996,
        "height": 443.1
      },
      "scale": 0.23074074074074072
    },
    "f02abbad-8c6a-4455-aa4f-49aab4a90427": {
      "position": {
        "x": 522.5,
        "y": 1856,
        "z": 5000
      },
      "rotation": {
        "x": 0,
        "y": 0,
        "z": 0,
        "w": 1
      },
      "viewCenter": {
        "x": 0,
        "y": 0,
        "z": 0
      },
      "contentRect": {
        "x": -273.9285714285714,
        "y": 638.5461772270284,
        "width": 611,
        "height": 934
      },
      "scale": 0.3835874439461884
    },
    "979d14c3-774d-4de5-b0bb-1454b69d5e61": {
      "position": {
        "x": 540,
        "y": 960.1685393258429,
        "z": 5000
      },
      "rotation": {
        "x": 0,
        "y": 0,
        "z": 0,
        "w": 1
      },
      "viewCenter": {
        "x": 0,
        "y": 0,
        "z": 0
      },
      "contentRect": {
        "x": 0,
        "y": 1.1368683772161603e-13,
        "width": 249.19999999999996,
        "height": 443.1
      },
      "scale": 0.23074074074074072
    },
    "a0f185e5-cbb7-4193-bc17-556ae1300262": {
      "position": {
        "x": 540,
        "y": 960.1685393258429,
        "z": 5000
      },
      "rotation": {
        "x": 0,
        "y": 0,
        "z": 0,
        "w": 1
      },
      "viewCenter": {
        "x": 0,
        "y": 0,
        "z": 0
      },
      "contentRect": {
        "x": 0,
        "y": 1.1368683772161603e-13,
        "width": 249.19999999999996,
        "height": 443.1
      },
      "scale": 0.23074074074074072
    },
    "ca4db1b9-9365-4ae5-9fc5-52cc7396c4f9": {
      "position": {
        "x": 540,
        "y": 960.1685393258429,
        "z": 5000
      },
      "rotation": {
        "x": 0,
        "y": 0,
        "z": 0,
        "w": 1
      },
      "viewCenter": {
        "x": 0,
        "y": 0,
        "z": 0
      },
      "contentRect": {
        "x": 0,
        "y": 1.1368683772161603e-13,
        "width": 249.19999999999996,
        "height": 443.1
      },
      "scale": 0.23074074074074072
    },
    "7f89a3f2-6bc9-4fb6-85fd-3515332a072b": {
      "position": {
        "x": 540,
        "y": 960.1685393258429,
        "z": 5000
      },
      "rotation": {
        "x": 0,
        "y": 0,
        "z": 0,
        "w": 1
      },
      "viewCenter": {
        "x": 0,
        "y": 0,
        "z": 0
      },
      "contentRect": {
        "x": 0,
        "y": 1.1368683772161603e-13,
        "width": 249.19999999999996,
        "height": 443.1
      },
      "scale": 0.23074074074074072
    },
    "df66b6d9-58e0-4714-8ce4-4a1af4432800": {
      "position": {
        "x": 540,
        "y": 960.1685393258429,
        "z": 5000
      },
      "rotation": {
        "x": 0,
        "y": 0,
        "z": 0,
        "w": 1
      },
      "viewCenter": {
        "x": 0,
        "y": 0,
        "z": 0
      },
      "contentRect": {
        "x": 0,
        "y": 1.1368683772161603e-13,
        "width": 249.19999999999996,
        "height": 443.1
      },
      "scale": 0.23074074074074072
    },
    "17c57859-9d33-4ea5-8c19-802be9790fbb": {
      "position": {
        "x": 540,
        "y": 960.1685393258429,
        "z": 5000
      },
      "rotation": {
        "x": 0,
        "y": 0,
        "z": 0,
        "w": 1
      },
      "viewCenter": {
        "x": 0,
        "y": 0,
        "z": 0
      },
      "contentRect": {
        "x": 0,
        "y": 1.1368683772161603e-13,
        "width": 249.19999999999996,
        "height": 443.1
      },
      "scale": 0.23074074074074072
    },
    "5e9e4e7f-5da9-4b52-b6dc-34ae7200fef4": {
      "position": {
        "x": 540,
        "y": 960.1685393258429,
        "z": 5000
      },
      "rotation": {
        "x": 0,
        "y": 0,
        "z": 0,
        "w": 1
      },
      "viewCenter": {
        "x": 0,
        "y": 0,
        "z": 0
      },
      "contentRect": {
        "x": 0,
        "y": 1.1368683772161603e-13,
        "width": 249.19999999999996,
        "height": 443.1
      },
      "scale": 0.23074074074074072
    },
    "41e79a76-942d-4f27-b94b-b704c1b6c33e": {
      "position": {
        "x": 540,
        "y": 960.1685393258429,
        "z": 5000
      },
      "rotation": {
        "x": 0,
        "y": 0,
        "z": 0,
        "w": 1
      },
      "viewCenter": {
        "x": 0,
        "y": 0,
        "z": 0
      },
      "contentRect": {
        "x": 0,
        "y": 1.1368683772161603e-13,
        "width": 249.19999999999996,
        "height": 443.1
      },
      "scale": 0.23074074074074072
    },
    "de0f6b4d-43f6-477c-9170-0a22e0cceb50": {
      "position": {
        "x": 860.3547527512083,
        "y": 1286.418014621393,
        "z": 5000
      },
      "rotation": {
        "x": 0,
        "y": 0,
        "z": 0,
        "w": 1
      },
      "viewCenter": {
        "x": 0,
        "y": 0,
        "z": 0
      },
      "contentRect": {
        "x": 231.52950981113713,
        "y": 325.1696072465543,
        "width": 611,
        "height": 934
      },
      "scale": 0.485826552654972
    },
    "451b2c50-4785-4df2-8648-2a5eff45dddc": {
      "position": {
        "x": 540,
        "y": 960.1685393258429,
        "z": 5000
      },
      "rotation": {
        "x": 0,
        "y": 0,
        "z": 0,
        "w": 1
      },
      "viewCenter": {
        "x": 0,
        "y": 0,
        "z": 0
      },
      "contentRect": {
        "x": 0,
        "y": 1.1368683772161603e-13,
        "width": 249.19999999999996,
        "height": 443.1
      },
      "scale": 0.23074074074074072
    },
    "1d19a6c8-9f85-4b92-810f-1c0f19bce9f2": {
      "position": {
        "x": 540,
        "y": 960.1685393258429,
        "z": 5000
      },
      "rotation": {
        "x": 0,
        "y": 0,
        "z": 0,
        "w": 1
      },
      "viewCenter": {
        "x": 0,
        "y": 0,
        "z": 0
      },
      "contentRect": {
        "x": 0,
        "y": 1.1368683772161603e-13,
        "width": 249.19999999999996,
        "height": 443.1
      },
      "scale": 0.23074074074074072
    },
    "85641579-f8d0-47e4-96ee-cd518b6235c7": {
      "position": {
        "x": 540,
        "y": 960.1685393258429,
        "z": 5000
      },
      "rotation": {
        "x": 0,
        "y": 0,
        "z": 0,
        "w": 1
      },
      "viewCenter": {
        "x": 0,
        "y": 0,
        "z": 0
      },
      "contentRect": {
        "x": 0,
        "y": 1.1368683772161603e-13,
        "width": 249.19999999999996,
        "height": 443.1
      },
      "scale": 0.23074074074074072
    },
    "96675dda-72bf-4ac1-83c1-be16de37bcf8": {
      "position": {
        "x": 540,
        "y": 960.1685393258429,
        "z": 5000
      },
      "rotation": {
        "x": 0,
        "y": 0,
        "z": 0,
        "w": 1
      },
      "viewCenter": {
        "x": 0,
        "y": 0,
        "z": 0
      },
      "contentRect": {
        "x": 0,
        "y": 1.1368683772161603e-13,
        "width": 249.19999999999996,
        "height": 443.1
      },
      "scale": 0.23074074074074072
    },
    "5886af90-c0b5-4717-bd59-75fdfbc8f145": {
      "position": {
        "x": 540,
        "y": 960.1685393258429,
        "z": 5000
      },
      "rotation": {
        "x": 0,
        "y": 0,
        "z": 0,
        "w": 1
      },
      "viewCenter": {
        "x": 0,
        "y": 0,
        "z": 0
      },
      "contentRect": {
        "x": 0,
        "y": 1.1368683772161603e-13,
        "width": 249.19999999999996,
        "height": 443.1
      },
      "scale": 0.23074074074074072
    },
    "d981959f-d320-4ee2-b6f3-4285fd82e8e2": {
      "position": {
        "x": 540,
        "y": 960.1685393258429,
        "z": 5000
      },
      "rotation": {
        "x": 0,
        "y": 0,
        "z": 0,
        "w": 1
      },
      "viewCenter": {
        "x": 0,
        "y": 0,
        "z": 0
      },
      "contentRect": {
        "x": 0,
        "y": 1.1368683772161603e-13,
        "width": 249.19999999999996,
        "height": 443.1
      },
      "scale": 0.23074074074074072
    },
    "b0ce5a4b-e920-43fb-82d3-f38bb042465a": {
      "position": {
        "x": 540,
        "y": 960.1685393258429,
        "z": 5000
      },
      "rotation": {
        "x": 0,
        "y": 0,
        "z": 0,
        "w": 1
      },
      "viewCenter": {
        "x": 0,
        "y": 0,
        "z": 0
      },
      "contentRect": {
        "x": 0,
        "y": 1.1368683772161603e-13,
        "width": 249.19999999999996,
        "height": 443.1
      },
      "scale": 0.23074074074074072
    },
    "cb63574e-203f-44bb-8507-6f0a780a4f94": {
      "position": {
        "x": 540,
        "y": 960.1685393258429,
        "z": 5000
      },
      "rotation": {
        "x": 0,
        "y": 0,
        "z": 0,
        "w": 1
      },
      "viewCenter": {
        "x": 0,
        "y": 0,
        "z": 0
      },
      "contentRect": {
        "x": 0,
        "y": 1.1368683772161603e-13,
        "width": 249.19999999999996,
        "height": 443.1
      },
      "scale": 0.23074074074074072
    },
    "1a7a4a05-efd6-4bfb-9305-b77b80f578f8": {
      "position": {
        "x": 540,
        "y": 960.1685393258429,
        "z": 5000
      },
      "rotation": {
        "x": 0,
        "y": 0,
        "z": 0,
        "w": 1
      },
      "viewCenter": {
        "x": 0,
        "y": 0,
        "z": 0
      },
      "contentRect": {
        "x": 0,
        "y": 1.1368683772161603e-13,
        "width": 249.19999999999996,
        "height": 443.1
      },
      "scale": 0.23074074074074072
    },
    "d5f1a023-c684-4fa2-9160-84bcc821a2eb": {
      "position": {
        "x": 540,
        "y": 960.1685393258429,
        "z": 5000
      },
      "rotation": {
        "x": 0,
        "y": 0,
        "z": 0,
        "w": 1
      },
      "viewCenter": {
        "x": 0,
        "y": 0,
        "z": 0
      },
      "contentRect": {
        "x": 0,
        "y": 1.1368683772161603e-13,
        "width": 249.19999999999996,
        "height": 443.1
      },
      "scale": 0.23074074074074072
    },
    "5c4a4484-39aa-46b5-90c3-b2374e7a6087": {
      "position": {
        "x": 412.1336023507383,
        "y": 676.1635937997561,
        "z": 5000
      },
      "rotation": {
        "x": 0,
        "y": 0,
        "z": 0,
        "w": 1
      },
      "viewCenter": {
        "x": 0,
        "y": 0,
        "z": 0
      },
      "contentRect": {
        "x": -375.3863708931486,
        "y": -837.3007169199772,
        "width": 486,
        "height": 934
      },
      "scale": 0.3085636025192537
    },
    "538f2c1d-85be-42e5-a1ce-73af46b8e5e5": {
      "position": {
        "x": 540,
        "y": 960.1685393258429,
        "z": 5000
      },
      "rotation": {
        "x": 0,
        "y": 0,
        "z": 0,
        "w": 1
      },
      "viewCenter": {
        "x": 0,
        "y": 0,
        "z": 0
      },
      "contentRect": {
        "x": 0,
        "y": 1.1368683772161603e-13,
        "width": 249.19999999999996,
        "height": 443.1
      },
      "scale": 0.23074074074074072
    },
    "0e55f785-1966-4539-b388-484aa08d44d5": {
      "position": {
        "x": 540,
        "y": 960.1685393258429,
        "z": 5000
      },
      "rotation": {
        "x": 0,
        "y": 0,
        "z": 0,
        "w": 1
      },
      "viewCenter": {
        "x": 0,
        "y": 0,
        "z": 0
      },
      "contentRect": {
        "x": 0,
        "y": 1.1368683772161603e-13,
        "width": 249.19999999999996,
        "height": 443.1
      },
      "scale": 0.23074074074074072
    },
    "7dc39a3b-0f70-46ae-99f0-429349ee80ef": {
      "position": {
        "x": 326.2099837606721,
        "y": 1834.32641153208,
        "z": 5000
      },
      "rotation": {
        "x": 0,
        "y": 0,
        "z": 0,
        "w": 1
      },
      "viewCenter": {
        "x": 0,
        "y": 0,
        "z": 0
      },
      "contentRect": {
        "x": -662.0992369604157,
        "y": -65.01682335165654,
        "width": 486,
        "height": 934
      },
      "scale": 0.245874464089997
    },
    "30edeaee-074d-4134-873f-24c8d317e159": {
      "position": {
        "x": 198.13015736110586,
        "y": 747.3129394115558,
        "z": 5000
      },
      "rotation": {
        "x": 0,
        "y": 0,
        "z": 0,
        "w": 1
      },
      "viewCenter": {
        "x": 0,
        "y": 0,
        "z": 0
      },
      "contentRect": {
        "x": -246.27551804786813,
        "y": -42.880298043164785,
        "width": 356,
        "height": 633
      },
      "scale": 0.4005349387948109
    }
  },
  "camera-uuids": [
    "f63c30f5-9b00-4554-bf40-5b498d0c477c",
    "c1bc1498-015a-4dd1-97b8-127884b52f31",
    "23f4bc2f-cb61-4569-8d05-89e8797959a9",
    "190151c2-7a08-4fb7-a224-af24a79e9fd2",
    "28c2dff9-1824-46ee-98ec-21aafdba0d73",
    "ea9c3c8c-ad25-4be1-b0fb-48652a4289c3",
    "8f4b7722-bdd9-4f92-9b39-7b944a1bb4b0",
    "98ff4829-3c5a-43bc-a42a-4697202840ec",
    "3b12c6fb-93c6-4f2d-9733-fd072f55d35d",
    "7b1ff178-765d-49e6-a1d3-0897373e0532",
    "c2ba1d29-5ca3-4e9d-8d11-0166ffc5b0c0",
    "e46b84c0-c2f0-42d6-b3cb-c5496df79b7a",
    "af08d2ac-23c4-4651-9230-aea1a154fd26",
    "677e48b9-ddcb-4482-8537-ed1f4bc7b9d1",
    "c9eaa10a-8107-4797-a73c-517650567f3f",
    "0124516a-207a-433c-b35b-af55e5f53a2c",
    "f402435c-a277-449f-8d0f-2312861d264c",
    "1ef0b093-4dbb-4bf2-b507-5d18b22bed20",
    "2957e9ed-0bc7-4938-8bab-a8031eb34703",
    "c04774ae-a060-4488-89d2-57984e1ae0f9",
    "e8e20e01-280d-41a6-977e-cd0a913a9cd5",
    "b36a2af2-cc8f-44d0-bb38-0dc6748c8223",
    "edfbd224-dffc-4a84-b2e6-2737f2c3d83e",
    "0f0183ae-8373-470c-801f-2d9bdd218678",
    "19e466cd-7354-4bb0-9458-98a49c902166",
    "f02abbad-8c6a-4455-aa4f-49aab4a90427",
    "979d14c3-774d-4de5-b0bb-1454b69d5e61",
    "a0f185e5-cbb7-4193-bc17-556ae1300262",
    "ca4db1b9-9365-4ae5-9fc5-52cc7396c4f9",
    "7f89a3f2-6bc9-4fb6-85fd-3515332a072b",
    "df66b6d9-58e0-4714-8ce4-4a1af4432800",
    "17c57859-9d33-4ea5-8c19-802be9790fbb",
    "5e9e4e7f-5da9-4b52-b6dc-34ae7200fef4",
    "41e79a76-942d-4f27-b94b-b704c1b6c33e",
    "de0f6b4d-43f6-477c-9170-0a22e0cceb50",
    "451b2c50-4785-4df2-8648-2a5eff45dddc",
    "1d19a6c8-9f85-4b92-810f-1c0f19bce9f2",
    "85641579-f8d0-47e4-96ee-cd518b6235c7",
    "96675dda-72bf-4ac1-83c1-be16de37bcf8",
    "5886af90-c0b5-4717-bd59-75fdfbc8f145",
    "d981959f-d320-4ee2-b6f3-4285fd82e8e2",
    "b0ce5a4b-e920-43fb-82d3-f38bb042465a",
    "cb63574e-203f-44bb-8507-6f0a780a4f94",
    "1a7a4a05-efd6-4bfb-9305-b77b80f578f8",
    "d5f1a023-c684-4fa2-9160-84bcc821a2eb",
    "5c4a4484-39aa-46b5-90c3-b2374e7a6087",
    "538f2c1d-85be-42e5-a1ce-73af46b8e5e5",
    "0e55f785-1966-4539-b388-484aa08d44d5",
    "7dc39a3b-0f70-46ae-99f0-429349ee80ef",
    "30edeaee-074d-4134-873f-24c8d317e159"
  ],
  "camera": {
    "color": [
      48,
      48,
      48,
      255
    ],
    "fov": 45,
    "far": 10000,
    "near": 0.01,
    "wheelSpeed": 0.01,
    "wanderSpeed": 10,
    "enableAcceleration": true,
    "size": "__default_design__",
    "far2D": 10000,
    "near2D": 1,
    "wheelSpeed2D": 6,
    "iso": 0,
    "aperture": 19,
    "shutter": 7
  },
  "scene_view": {
    "isSceneLightOn": true,
    "output_device": "__default_design__"
  },
  "game-view": {
    "scaleValue": 33,
    "sliderValue": 13,
    "devicesInfo": {
      "name": "i18n:scene.game_view.design_resolution",
      "type": "design",
      "width": 1080,
      "height": 1920
    },
    "fps": 60
  }
}
